Workbook

Sheet Expense Tracker
A1: DATE | B1: DESCRIPTION | C1: CATEGORY | D1: TYPE | E1: AMOUNT | F1: PAYMENT METHOD
A2: 46296 | B2: Monthly allowance | C2: Income | D2: Income | E2: 12000 | F2: Bank
A3: 46297 | B3: Hostel fee | C3: Accommodation | D3: Expense | E3: 6000 | F3: Bank
A4: 46298 | B4: Snacks | C4: Food | D4: Expense | E4: 100 | F4: UPI
A5: 46299 | B5: Bus fare | C5: Transport | D5: Expense | E5: 50 | F5: UPI
A6: 46300 | B6: Breakfast | C6: Food | D6: Expense | E6: 60 | F6: UPI
A7: 46300 | B7: Mobile recharge | C7: Mobile & Internet | D7: Expense | E7: 299 | F7: UPI
A8: 46301 | B8: Lunch | C8: Food | D8: Expense | E8: 100 | F8: UPI
A9: 46301 | B9: Notebook and pens | C9: Education | D9: Expense | E9: 180 | F9: Cash
A10: 46302 | B10: Bus fare | C10: Transport | D10: Expense | E10: 50 | F10: UPI
A11: 46302 | B11: Evening snacks | C11: Food | D11: Expense | E11: 80 | F11: Cash
A12: 46303 | B12: Laundry | C12: Personal Care | D12: Expense | E12: 120 | F12: UPI
A13: 46303 | B13: Movie ticket | C13: Entertainment | D13: Expense | E13: 250 | F13: UPI
... A35: 46318 | B35: Monthly allowance | C35: Income | D35: Income | E35: 3000 | F35: Bank

Sheet Summary
A1: SMARTSPEND — STUDENT BUDGET DASHBOARD
A3: Total Income | B3: =SUMIF('Expense Tracker'!D:D,"Income",'Expense Tracker'!E:E) -> 18500
A4: Total Expenses | B4: =SUMIF('Expense Tracker'!D:D,"Expense",'Expense Tracker'!E:E) -> 11621
A5: Remaining Balance | B5: =B3-B4 -> 6879
A6: Savings Rate | B6: =IFERROR(B5/B3,0) -> 0.37183784
A8: Expense Category | B8: Total Spent
A9: Food | B9: =SUMIFS('Expense Tracker'!E:E,'Expense Tracker'!C:C,A9,'Expense Tracker'!D:D,"Expense") -> 1225
A10: Accommodation | B10: =SUMIFS('Expense Tracker'!E:E,'Expense Tracker'!C:C,A10,'Expense Tracker'!D:D,"Expense") -> 6250
A11: Transport | B11: =SUMIFS('Expense Tracker'!E:E,'Expense Tracker'!C:C,A11,'Expense Tracker'!D:D,"Expense") -> 770
A12: Education | B12: =SUMIFS('Expense Tracker'!E:E,'Expense Tracker'!C:C,A12,'Expense Tracker'!D:D,"Expense") -> 969
A13: Mobile & Internet | B13: =SUMIFS('Expense Tracker'!E:E,'Expense Tracker'!C:C,A13,'Expense Tracker'!D:D,"Expense") -> 498
A14: Entertainment | B14: =SUMIFS('Expense Tracker'!E:E,'Expense Tracker'!C:C,A14,'Expense Tracker'!D:D,"Expense") -> 700
A15: Personal Care | B15: =SUMIFS('Expense Tracker'!E:E,'Expense Tracker'!C:C,A15,'Expense Tracker'!D:D,"Expense") -> 430
A16: Shopping | B16: =SUMIFS('Expense Tracker'!E:E,'Expense Tracker'!C:C,A16,'Expense Tracker'!D:D,"Expense") -> 599
A17: Health | B17: =SUMIFS('Expense Tracker'!E:E,'Expense Tracker'!C:C,A17,'Expense Tracker'!D:D,"Expense") -> 180
A19: Monthly Savings Goal | B19: 3000
A20: Goal Status | B20: =IF(B5>=B19,"GOAL ACHIEVED","KEEP SAVING") -> GOAL ACHIEVED

Sheet Budget
A1: CATEGORY | B1: MONTHLY BUDGET (₹) | C1: ACTUAL SPENDING | D1: BUDGET STATUS | E1: Remaining Budget (₹)
A2: Food | B2: 3000 | C2: =SUMIFS('Expense Tracker'!E:E,'Expense Tracker'!C:C,A2,'Expense Tracker'!D:D,"Expense") -> 1225 | D2: =IF(C2>B2,"OVER BUDGET",IF(C2=B2,"BUDGET USED","WITHIN BUDGET")) -> WITHIN BUDGET | E2: =B2-C2 -> 1775
A3: Accomodation | B3: 6500 | C3: =SUMIFS('Expense Tracker'!E:E,'Expense Tracker'!C:C,A3,'Expense Tracker'!D:D,"Expense") -> 0 | D3: =IF(C3>B3,"OVER BUDGET",IF(C3=B3,"BUDGET USED","WITHIN BUDGET")) -> WITHIN BUDGET | E3: =B3-C3 -> 6500
A4: Transport | B4: 1000 | C4: =SUMIFS('Expense Tracker'!E:E,'Expense Tracker'!C:C,A4,'Expense Tracker'!D:D,"Expense") -> 770 | D4: =IF(C4>B4,"OVER BUDGET",IF(C4=B4,"BUDGET USED","WITHIN BUDGET")) -> WITHIN BUDGET | E4: =B4-C4 -> 230
A5: Education | B5: 1000 | C5: =SUMIFS('Expense Tracker'!E:E,'Expense Tracker'!C:C,A5,'Expense Tracker'!D:D,"Expense") -> 969 | D5: =IF(C5>B5,"OVER BUDGET",IF(C5=B5,"BUDGET USED","WITHIN BUDGET")) -> WITHIN BUDGET | E5: =B5-C5 -> 31
A6: Mobile & Internet | B6: 500 | C6: =SUMIFS('Expense Tracker'!E:E,'Expense Tracker'!C:C,A6,'Expense Tracker'!D:D,"Expense") -> 498 | D6: =IF(C6>B6,"OVER BUDGET",IF(C6=B6,"BUDGET USED","WITHIN BUDGET")) -> WITHIN BUDGET | E6: =B6-C6 -> 2
A7: Entertainment | B7: 800 | C7: =SUMIFS('Expense Tracker'!E:E,'Expense Tracker'!C:C,A7,'Expense Tracker'!D:D,"Expense") -> 700 | D7: =IF(C7>B7,"OVER BUDGET",IF(C7=B7,"BUDGET USED","WITHIN BUDGET")) -> WITHIN BUDGET | E7: =B7-C7 -> 100
A8: Personal Care | B8: 500 | C8: =SUMIFS('Expense Tracker'!E:E,'Expense Tracker'!C:C,A8,'Expense Tracker'!D:D,"Expense") -> 430 | D8: =IF(C8>B8,"OVER BUDGET",IF(C8=B8,"BUDGET USED","WITHIN BUDGET")) -> WITHIN BUDGET | E8: =B8-C8 -> 70
A9: Shopping | B9: 500 | C9: =SUMIFS('Expense Tracker'!E:E,'Expense Tracker'!C:C,A9,'Expense Tracker'!D:D,"Expense") -> 599 | D9: =IF(C9>B9,"OVER BUDGET",IF(C9=B9,"BUDGET USED","WITHIN BUDGET")) -> OVER BUDGET | E9: =B9-C9 -> -99
A10: Health | B10: 500 | C10: =SUMIFS('Expense Tracker'!E:E,'Expense Tracker'!C:C,A10,'Expense Tracker'!D:D,"Expense") -> 180 | D10: =IF(C10>B10,"OVER BUDGET",IF(C10=B10,"BUDGET USED","WITHIN BUDGET")) -> WITHIN BUDGET | E10: =B10-C10 -> 320
